osio_flylord/__init__.py
osio_flylord/osio.py
osio-0.0.1.dist-info/LICENSE
osio-0.0.1.dist-info/METADATA
osio-0.0.1.dist-info/WHEEL
osio-0.0.1.dist-info/top_level.txt
osio-0.0.1.dist-info/RECORD
