Metadata-Version: 2.1
Name: osio
Version: 0.0.1
Summary: consolidation file and folder commands
Author-email: fly lord <fox21@foxjazz.net>
Project-URL: Homepage, https://github.com/foxjazz/python-osio
Classifier: Programming Language :: Python :: 3
Classifier: License :: OSI Approved :: MIT License
Classifier: Operating System :: OS Independent
Requires-Python: >=3.7
License-File: LICENSE
